cfscan/__init__.py
cfscan/cfscanner.py
cfscan/scanner.py
cfscan-0.0.4.data/scripts/cfscan
cfscan-0.0.4.dist-info/METADATA
cfscan-0.0.4.dist-info/RECORD
cfscan-0.0.4.dist-info/WHEEL
cfscan-0.0.4.dist-info/top_level.txt
