Metadata-Version: 2.1
Name: cfscan
Version: 0.0.4
Summary: cfscan is an open source vulnerability scanner for cloud foundry
Home-page: https://github.com/cloudhound-io/cfscan
Author: https://cloudhound.io
Author-email: info@cloudhound.io
License: BSD
Keywords: free open-source cf cloud foundry cloudfoundry security health vulnerability scanner
Platform: UNKNOWN
Classifier: Development Status :: 3 - Alpha
Classifier: Topic :: Utilities
Classifier: License :: OSI Approved :: BSD License
Requires-Dist: requests
